handposeutils/__init__.py
handposeutils/calculations/__init__.py
handposeutils/calculations/geometry.py
handposeutils/calculations/similarity.py
handposeutils/calculations/transforms.py
handposeutils/data/__init__.py
handposeutils/data/constants.py
handposeutils/data/coordinate.py
handposeutils/data/data_reader.py
handposeutils/data/handpose.py
handposeutils/data/handpose_sequence.py
handposeutils/embeddings/__init__.py
handposeutils/embeddings/vector.py
handposeutils/visualization/__init__.py
handposeutils/visualization/visualized_pose.py
handposeutils/visualization/visualizer.py
handposeutils-0.1.7.dist-info/licenses/LICENSE
handposeutils-0.1.7.dist-info/METADATA
handposeutils-0.1.7.dist-info/WHEEL
handposeutils-0.1.7.dist-info/top_level.txt
handposeutils-0.1.7.dist-info/RECORD
