Metadata-Version: 2.4
Name: handposeutils
Version: 0.1.7
Summary: Utilities for hand pose processing
Author-email: Ishan Pendyala <pendyala.ishan@gmail.com>, Ethan Praisoody <ethanpraisoody@gmail.com>
License: MIT
Keywords: hand pose,mediapipe,3D visualization,Open3D,research
License-File: LICENSE
Requires-Dist: open3d==0.19.0
Requires-Dist: numpy>=1.26.4
Requires-Dist: mediapipe==0.10.11
Requires-Dist: opencv-python>=4.10.0.82
Requires-Dist: matplotlib
Dynamic: license-file
